README
setup.py
mypypiproject/__init__.py
mypypiproject/useful.py
mypypiproject.egg-info/PKG-INFO
mypypiproject.egg-info/SOURCES.txt
mypypiproject.egg-info/dependency_links.txt
mypypiproject.egg-info/top_level.txt
tests/__init__.py
tests/runall.py