Metadata-Version: 1.0
Name: mypypiproject
Version: 0.0.4
Summary: A demo
Home-page: http://packages.python.org/mypypiproject
Author: David Daniels
Author-email: david8381@gmail.com
License: BSD
Keywords: example doc tutorial
Platform: UNKNOWN
